{
    "tree": {
        "ff9d924e-c8e9-4367-892f-b1fb1c9380fa": {
            "name": "C0",
            "category": "Fallback",
            "memory": false,
            "children": [
                "377ce734-b1bc-4c5f-8b4b-e7c65967db60",
                "b109ae44-16ac-4d16-beb5-3e79fb53275e",
                "071ceb27-dfd3-43d3-a154-9bb7b465dde6"
            ]
        },
        "377ce734-b1bc-4c5f-8b4b-e7c65967db60": {
            "name": "L0",
            "category": "Condition",
            "description": "Random condition node",
            "class": "RandomConditionNode",
            "module": "btcm.examples.random.random_bt"
        },
        "b109ae44-16ac-4d16-beb5-3e79fb53275e": {
            "name": "C1",
            "category": "Fallback",
            "memory": false,
            "children": [
                "b3940b69-3321-46ca-a973-250ec17ebef3",
                "35e340e0-f80c-4571-9376-77d2c163bee5"
            ]
        },
        "b3940b69-3321-46ca-a973-250ec17ebef3": {
            "name": "L1",
            "category": "Action",
            "description": "Random action node",
            "class": "RandomActionNode",
            "module": "btcm.examples.random.random_bt"
        },
        "35e340e0-f80c-4571-9376-77d2c163bee5": {
            "name": "C2",
            "category": "Sequence",
            "memory": false,
            "children": [
                "08082c67-e4e4-471b-96d1-f8edac276564",
                "2cddc062-c803-43ed-85ea-f71734281d9f"
            ]
        },
        "08082c67-e4e4-471b-96d1-f8edac276564": {
            "name": "C3",
            "category": "Fallback",
            "memory": false,
            "children": [
                "d64574f3-a464-48f9-8104-4e11f024671f",
                "283a4426-a90d-4e2a-986b-bb00fe849a5e"
            ]
        },
        "d64574f3-a464-48f9-8104-4e11f024671f": {
            "name": "L4",
            "category": "Action",
            "description": "Random action node",
            "class": "RandomActionNode",
            "module": "btcm.examples.random.random_bt"
        },
        "283a4426-a90d-4e2a-986b-bb00fe849a5e": {
            "name": "L5",
            "category": "Action",
            "description": "Random action node",
            "class": "RandomActionNode",
            "module": "btcm.examples.random.random_bt"
        },
        "2cddc062-c803-43ed-85ea-f71734281d9f": {
            "name": "C4",
            "category": "Sequence",
            "memory": false,
            "children": [
                "bc1d010a-5c42-4eca-9d6b-20aa2b513918",
                "c79292d0-6e5b-4f63-af24-77c7d53b899b",
                "b770adda-5174-4b56-84f0-031832d4b70d"
            ]
        },
        "bc1d010a-5c42-4eca-9d6b-20aa2b513918": {
            "name": "L2",
            "category": "Action",
            "description": "Random action node",
            "class": "RandomActionNode",
            "module": "btcm.examples.random.random_bt"
        },
        "c79292d0-6e5b-4f63-af24-77c7d53b899b": {
            "name": "L3",
            "category": "Condition",
            "description": "Random condition node",
            "class": "RandomConditionNode",
            "module": "btcm.examples.random.random_bt"
        },
        "b770adda-5174-4b56-84f0-031832d4b70d": {
            "name": "L6",
            "category": "Condition",
            "description": "Random condition node",
            "class": "RandomConditionNode",
            "module": "btcm.examples.random.random_bt"
        },
        "071ceb27-dfd3-43d3-a154-9bb7b465dde6": {
            "name": "L7",
            "category": "Condition",
            "description": "Random condition node",
            "class": "RandomConditionNode",
            "module": "btcm.examples.random.random_bt"
        }
    },
    "state": {
        "variables": {
            "T1": "T1 is a variable in the random state.",
            "T2": "T2 is a variable in the random state.",
            "T3": "T3 is a variable in the random state.",
            "T4": "T4 is a variable in the random state.",
            "I1": "I1 is a variable in the random state.",
            "I2": "I2 is a variable in the random state.",
            "B1": "B1 is a variable in the random state.",
            "B2": "B2 is a variable in the random state."
        },
        "class": "RandomState",
        "module": "btcm.examples.random.random_state"
    },
    "0": {
        "0": {
            "state": {
                "T1": true,
                "T2": false,
                "T3": true,
                "T4": true,
                "I1": true,
                "I2": true,
                "B1": true,
                "B2": true
            }
        },
        "1": {
            "update": {
                "377ce734-b1bc-4c5f-8b4b-e7c65967db60": {
                    "name": "L0",
                    "status": "Status.SUCCESS",
                    "action": "NullAction"
                }
            },
            "state": {
                "T1": true,
                "T2": false,
                "T3": true,
                "T4": true,
                "I1": true,
                "I2": true,
                "B1": true,
                "B2": true
            }
        },
        "2": {
            "update": {
                "ff9d924e-c8e9-4367-892f-b1fb1c9380fa": {
                    "name": "C0",
                    "status": "Status.SUCCESS"
                }
            },
            "state": {
                "T1": true,
                "T2": false,
                "T3": true,
                "T4": true,
                "I1": true,
                "I2": true,
                "B1": true,
                "B2": true
            }
        }
    }
}