{
    "tree": {
        "fb0090f9-cb3c-450b-a4ea-25c9177aa312": {
            "name": "C0",
            "category": "Fallback",
            "memory": false,
            "children": [
                "a2ec32a2-ad09-4598-8834-5a48128738a0",
                "30064617-2ba1-44d3-b14b-244f8d18d0a4",
                "bff3f961-f978-449c-9250-6e4ecdca40e1",
                "e09cccb9-7a12-4df6-9b34-ed5fdc4d5bd4"
            ]
        },
        "a2ec32a2-ad09-4598-8834-5a48128738a0": {
            "name": "L0",
            "category": "Action",
            "description": "Random action node",
            "class": "RandomActionNode",
            "module": "btcm.examples.random.random_bt"
        },
        "30064617-2ba1-44d3-b14b-244f8d18d0a4": {
            "name": "L1",
            "category": "Condition",
            "description": "Random condition node",
            "class": "RandomConditionNode",
            "module": "btcm.examples.random.random_bt"
        },
        "bff3f961-f978-449c-9250-6e4ecdca40e1": {
            "name": "C1",
            "category": "Fallback",
            "memory": false,
            "children": [
                "f359b371-1d34-4701-a9a6-1f3f79e0d13a",
                "379ac4ff-d587-4f6c-9eba-79ae2dde502a"
            ]
        },
        "f359b371-1d34-4701-a9a6-1f3f79e0d13a": {
            "name": "L2",
            "category": "Action",
            "description": "Random action node",
            "class": "RandomActionNode",
            "module": "btcm.examples.random.random_bt"
        },
        "379ac4ff-d587-4f6c-9eba-79ae2dde502a": {
            "name": "C2",
            "category": "Fallback",
            "memory": false,
            "children": [
                "bf3b4474-3ee4-4ffe-a1d4-4564d98aa8a6",
                "4dcfdab7-80ae-4e15-b8bc-1fd27acf9dc9"
            ]
        },
        "bf3b4474-3ee4-4ffe-a1d4-4564d98aa8a6": {
            "name": "C3",
            "category": "Sequence",
            "memory": false,
            "children": [
                "e666ed18-2f4d-42f5-ac41-3fae18a3c6c0",
                "dc0ea338-1c6b-4eed-adfa-378e53f9d1cf",
                "83dba6e0-8a5c-48b3-bb4f-9f61e9ffd04d"
            ]
        },
        "e666ed18-2f4d-42f5-ac41-3fae18a3c6c0": {
            "name": "L5",
            "category": "Action",
            "description": "Random action node",
            "class": "RandomActionNode",
            "module": "btcm.examples.random.random_bt"
        },
        "dc0ea338-1c6b-4eed-adfa-378e53f9d1cf": {
            "name": "L6",
            "category": "Condition",
            "description": "Random condition node",
            "class": "RandomConditionNode",
            "module": "btcm.examples.random.random_bt"
        },
        "83dba6e0-8a5c-48b3-bb4f-9f61e9ffd04d": {
            "name": "L7",
            "category": "Action",
            "description": "Random action node",
            "class": "RandomActionNode",
            "module": "btcm.examples.random.random_bt"
        },
        "4dcfdab7-80ae-4e15-b8bc-1fd27acf9dc9": {
            "name": "L3",
            "category": "Condition",
            "description": "Random condition node",
            "class": "RandomConditionNode",
            "module": "btcm.examples.random.random_bt"
        },
        "e09cccb9-7a12-4df6-9b34-ed5fdc4d5bd4": {
            "name": "L4",
            "category": "Action",
            "description": "Random action node",
            "class": "RandomActionNode",
            "module": "btcm.examples.random.random_bt"
        }
    },
    "state": {
        "variables": {
            "T1": "T1 is a variable in the random state.",
            "T2": "T2 is a variable in the random state.",
            "I1": "I1 is a variable in the random state.",
            "B1": "B1 is a variable in the random state."
        },
        "class": "RandomState",
        "module": "btcm.examples.random.random_state"
    },
    "0": {
        "0": {
            "state": {
                "T1": true,
                "T2": false,
                "I1": false,
                "B1": false
            }
        },
        "1": {
            "update": {
                "a2ec32a2-ad09-4598-8834-5a48128738a0": {
                    "name": "L0",
                    "status": "Status.SUCCESS",
                    "action": "RandomAction2"
                }
            },
            "state": {
                "T1": false,
                "T2": false,
                "I1": false,
                "B1": false
            }
        },
        "2": {
            "update": {
                "fb0090f9-cb3c-450b-a4ea-25c9177aa312": {
                    "name": "C0",
                    "status": "Status.SUCCESS"
                }
            },
            "state": {
                "T1": false,
                "T2": false,
                "I1": false,
                "B1": false
            }
        }
    }
}