{
    "tree": {
        "2be69eeb-f3d5-48d7-a1c5-12d951073fc1": {
            "name": "C0",
            "category": "Fallback",
            "memory": false,
            "children": [
                "5e8c7d44-3b8b-4c96-b2b9-02ae985d333a",
                "f3d92780-7373-4a39-b044-2c925452adaf",
                "9519c9c0-5f3f-47bc-8a7c-2fbff1484e3c",
                "92a4b193-5a19-418a-b5b6-45de9ea47fe0"
            ]
        },
        "5e8c7d44-3b8b-4c96-b2b9-02ae985d333a": {
            "name": "L0",
            "category": "Condition",
            "description": "Random condition node",
            "class": "RandomConditionNode",
            "module": "btcm.examples.random.random_bt"
        },
        "f3d92780-7373-4a39-b044-2c925452adaf": {
            "name": "L1",
            "category": "Action",
            "description": "Random action node",
            "class": "RandomActionNode",
            "module": "btcm.examples.random.random_bt"
        },
        "9519c9c0-5f3f-47bc-8a7c-2fbff1484e3c": {
            "name": "L2",
            "category": "Condition",
            "description": "Random condition node",
            "class": "RandomConditionNode",
            "module": "btcm.examples.random.random_bt"
        },
        "92a4b193-5a19-418a-b5b6-45de9ea47fe0": {
            "name": "L3",
            "category": "Action",
            "description": "Random action node",
            "class": "RandomActionNode",
            "module": "btcm.examples.random.random_bt"
        }
    },
    "state": {
        "variables": {
            "T1": "T1 is a variable in the random state.",
            "T2": "T2 is a variable in the random state.",
            "I1": "I1 is a variable in the random state.",
            "B1": "B1 is a variable in the random state."
        },
        "class": "RandomState",
        "module": "btcm.examples.random.random_state"
    },
    "0": {
        "0": {
            "state": {
                "T1": true,
                "T2": true,
                "I1": false,
                "B1": false
            }
        },
        "1": {
            "update": {
                "5e8c7d44-3b8b-4c96-b2b9-02ae985d333a": {
                    "name": "L0",
                    "status": "Status.SUCCESS",
                    "action": "NullAction"
                }
            },
            "state": {
                "T1": true,
                "T2": true,
                "I1": false,
                "B1": false
            }
        },
        "2": {
            "update": {
                "2be69eeb-f3d5-48d7-a1c5-12d951073fc1": {
                    "name": "C0",
                    "status": "Status.SUCCESS"
                }
            },
            "state": {
                "T1": true,
                "T2": true,
                "I1": false,
                "B1": false
            }
        }
    }
}