{
    "tree": {
        "4c7641dd-ddb5-4b46-b5bf-a85401fea4ff": {
            "name": "C0",
            "category": "Fallback",
            "memory": false,
            "children": [
                "cd8ef7a1-0aaf-41c1-bd04-b10e99133b5e",
                "95e27be1-34a9-4614-a80c-256c7c4b3be0",
                "0a93323e-5bfc-4d74-bc89-d1debd361267",
                "151f21c3-36fa-4605-808b-91b345c0e09b"
            ]
        },
        "cd8ef7a1-0aaf-41c1-bd04-b10e99133b5e": {
            "name": "L0",
            "category": "Condition",
            "description": "Random condition node",
            "class": "RandomConditionNode",
            "module": "btcm.examples.random.random_bt"
        },
        "95e27be1-34a9-4614-a80c-256c7c4b3be0": {
            "name": "L1",
            "category": "Action",
            "description": "Random action node",
            "class": "RandomActionNode",
            "module": "btcm.examples.random.random_bt"
        },
        "0a93323e-5bfc-4d74-bc89-d1debd361267": {
            "name": "C1",
            "category": "Fallback",
            "memory": false,
            "children": [
                "de0b95aa-c6ab-48b0-9a15-7e367e49135f",
                "4e79829f-9098-4bfe-af43-66d3ff4e3c99",
                "38566eec-913c-4316-a1f6-09e904641981",
                "7bbdb2fa-099b-4752-9c30-e6d51c9666f4"
            ]
        },
        "de0b95aa-c6ab-48b0-9a15-7e367e49135f": {
            "name": "L2",
            "category": "Condition",
            "description": "Random condition node",
            "class": "RandomConditionNode",
            "module": "btcm.examples.random.random_bt"
        },
        "4e79829f-9098-4bfe-af43-66d3ff4e3c99": {
            "name": "C2",
            "category": "Fallback",
            "memory": false,
            "children": [
                "cde4bdf9-6911-471e-87f8-6f09dfe57892",
                "25148aed-90f3-4cee-b3d9-ba85f2af1df3"
            ]
        },
        "cde4bdf9-6911-471e-87f8-6f09dfe57892": {
            "name": "L3",
            "category": "Condition",
            "description": "Random condition node",
            "class": "RandomConditionNode",
            "module": "btcm.examples.random.random_bt"
        },
        "25148aed-90f3-4cee-b3d9-ba85f2af1df3": {
            "name": "L4",
            "category": "Action",
            "description": "Random action node",
            "class": "RandomActionNode",
            "module": "btcm.examples.random.random_bt"
        },
        "38566eec-913c-4316-a1f6-09e904641981": {
            "name": "L6",
            "category": "Condition",
            "description": "Random condition node",
            "class": "RandomConditionNode",
            "module": "btcm.examples.random.random_bt"
        },
        "7bbdb2fa-099b-4752-9c30-e6d51c9666f4": {
            "name": "L7",
            "category": "Action",
            "description": "Random action node",
            "class": "RandomActionNode",
            "module": "btcm.examples.random.random_bt"
        },
        "151f21c3-36fa-4605-808b-91b345c0e09b": {
            "name": "L5",
            "category": "Action",
            "description": "Random action node",
            "class": "RandomActionNode",
            "module": "btcm.examples.random.random_bt"
        }
    },
    "state": {
        "variables": {
            "T1": "T1 is a variable in the random state.",
            "T2": "T2 is a variable in the random state.",
            "T3": "T3 is a variable in the random state.",
            "T4": "T4 is a variable in the random state.",
            "I1": "I1 is a variable in the random state.",
            "I2": "I2 is a variable in the random state.",
            "B1": "B1 is a variable in the random state.",
            "B2": "B2 is a variable in the random state."
        },
        "class": "RandomState",
        "module": "btcm.examples.random.random_state"
    },
    "0": {
        "0": {
            "state": {
                "T1": true,
                "T2": false,
                "T3": false,
                "T4": false,
                "I1": true,
                "I2": false,
                "B1": true,
                "B2": false
            }
        },
        "1": {
            "update": {
                "cd8ef7a1-0aaf-41c1-bd04-b10e99133b5e": {
                    "name": "L0",
                    "status": "Status.SUCCESS",
                    "action": "NullAction"
                }
            },
            "state": {
                "T1": true,
                "T2": false,
                "T3": false,
                "T4": false,
                "I1": true,
                "I2": false,
                "B1": true,
                "B2": false
            }
        },
        "2": {
            "update": {
                "4c7641dd-ddb5-4b46-b5bf-a85401fea4ff": {
                    "name": "C0",
                    "status": "Status.SUCCESS"
                }
            },
            "state": {
                "T1": true,
                "T2": false,
                "T3": false,
                "T4": false,
                "I1": true,
                "I2": false,
                "B1": true,
                "B2": false
            }
        }
    }
}