{
    "tree": {
        "fca6fdbb-dcee-4b5a-9698-9ab8bce47b8b": {
            "name": "C0",
            "category": "Fallback",
            "memory": false,
            "children": [
                "54752456-03e6-42e4-b73d-613dc2fceb57",
                "bd9eebfc-2f57-4ead-8634-a61865022272",
                "c3be0ee2-d59e-4db3-a47f-bcd034d3e0ae",
                "a760cbff-ca35-4862-a55f-a638ffd561ea"
            ]
        },
        "54752456-03e6-42e4-b73d-613dc2fceb57": {
            "name": "L0",
            "category": "Condition",
            "description": "Random condition node",
            "class": "RandomConditionNode",
            "module": "btcm.examples.random.random_bt"
        },
        "bd9eebfc-2f57-4ead-8634-a61865022272": {
            "name": "L1",
            "category": "Action",
            "description": "Random action node",
            "class": "RandomActionNode",
            "module": "btcm.examples.random.random_bt"
        },
        "c3be0ee2-d59e-4db3-a47f-bcd034d3e0ae": {
            "name": "L2",
            "category": "Condition",
            "description": "Random condition node",
            "class": "RandomConditionNode",
            "module": "btcm.examples.random.random_bt"
        },
        "a760cbff-ca35-4862-a55f-a638ffd561ea": {
            "name": "L3",
            "category": "Condition",
            "description": "Random condition node",
            "class": "RandomConditionNode",
            "module": "btcm.examples.random.random_bt"
        }
    },
    "state": {
        "variables": {
            "T1": "T1 is a variable in the random state.",
            "T2": "T2 is a variable in the random state.",
            "T3": "T3 is a variable in the random state.",
            "T4": "T4 is a variable in the random state.",
            "I1": "I1 is a variable in the random state.",
            "I2": "I2 is a variable in the random state.",
            "B1": "B1 is a variable in the random state.",
            "B2": "B2 is a variable in the random state."
        },
        "class": "RandomState",
        "module": "btcm.examples.random.random_state"
    },
    "0": {
        "0": {
            "state": {
                "T1": false,
                "T2": true,
                "T3": false,
                "T4": false,
                "I1": true,
                "I2": true,
                "B1": false,
                "B2": false
            }
        },
        "1": {
            "update": {
                "54752456-03e6-42e4-b73d-613dc2fceb57": {
                    "name": "L0",
                    "status": "Status.FAILURE",
                    "action": "NullAction"
                }
            },
            "state": {
                "T1": false,
                "T2": true,
                "T3": false,
                "T4": false,
                "I1": true,
                "I2": true,
                "B1": false,
                "B2": false
            }
        },
        "2": {
            "update": {
                "bd9eebfc-2f57-4ead-8634-a61865022272": {
                    "name": "L1",
                    "status": "Status.SUCCESS",
                    "action": "RandomAction1"
                }
            },
            "state": {
                "T1": false,
                "T2": true,
                "T3": false,
                "T4": false,
                "I1": true,
                "I2": true,
                "B1": false,
                "B2": false
            }
        },
        "3": {
            "update": {
                "fca6fdbb-dcee-4b5a-9698-9ab8bce47b8b": {
                    "name": "C0",
                    "status": "Status.SUCCESS"
                }
            },
            "state": {
                "T1": false,
                "T2": true,
                "T3": false,
                "T4": false,
                "I1": true,
                "I2": true,
                "B1": false,
                "B2": false
            }
        }
    }
}