{
    "tree": {
        "79cf8073-b5f2-4359-a5b0-3bb3c68bce38": {
            "name": "C0",
            "category": "Fallback",
            "memory": false,
            "children": [
                "36c07167-b215-42fa-a22a-45da71b31e9d",
                "84946059-dbd2-49e8-988d-6d2af224957e",
                "a8894abf-7ace-4a54-b4a5-44444ad64835",
                "b79b5f3c-8d26-4a41-996a-b74fc42573cc"
            ]
        },
        "36c07167-b215-42fa-a22a-45da71b31e9d": {
            "name": "L0",
            "category": "Condition",
            "description": "Random condition node",
            "class": "RandomConditionNode",
            "module": "btcm.examples.random.random_bt"
        },
        "84946059-dbd2-49e8-988d-6d2af224957e": {
            "name": "L1",
            "category": "Condition",
            "description": "Random condition node",
            "class": "RandomConditionNode",
            "module": "btcm.examples.random.random_bt"
        },
        "a8894abf-7ace-4a54-b4a5-44444ad64835": {
            "name": "C1",
            "category": "Fallback",
            "memory": false,
            "children": [
                "8bd5c731-3a25-48ad-98a6-e3f51efa7135",
                "c90dbba3-d43d-4f1c-b5aa-59a23239e6bb",
                "a3e9da1b-1596-41ca-b00f-02846f0c8cd7",
                "404d0139-f82f-474f-938d-52b3bfb33094"
            ]
        },
        "8bd5c731-3a25-48ad-98a6-e3f51efa7135": {
            "name": "L2",
            "category": "Condition",
            "description": "Random condition node",
            "class": "RandomConditionNode",
            "module": "btcm.examples.random.random_bt"
        },
        "c90dbba3-d43d-4f1c-b5aa-59a23239e6bb": {
            "name": "C2",
            "category": "Fallback",
            "memory": false,
            "children": [
                "54896c46-a204-4dac-a1ca-5a4578683786",
                "5076edc0-ccfa-4a94-a63b-7568652c4bd1"
            ]
        },
        "54896c46-a204-4dac-a1ca-5a4578683786": {
            "name": "L3",
            "category": "Condition",
            "description": "Random condition node",
            "class": "RandomConditionNode",
            "module": "btcm.examples.random.random_bt"
        },
        "5076edc0-ccfa-4a94-a63b-7568652c4bd1": {
            "name": "L4",
            "category": "Action",
            "description": "Random action node",
            "class": "RandomActionNode",
            "module": "btcm.examples.random.random_bt"
        },
        "a3e9da1b-1596-41ca-b00f-02846f0c8cd7": {
            "name": "L6",
            "category": "Action",
            "description": "Random action node",
            "class": "RandomActionNode",
            "module": "btcm.examples.random.random_bt"
        },
        "404d0139-f82f-474f-938d-52b3bfb33094": {
            "name": "L7",
            "category": "Action",
            "description": "Random action node",
            "class": "RandomActionNode",
            "module": "btcm.examples.random.random_bt"
        },
        "b79b5f3c-8d26-4a41-996a-b74fc42573cc": {
            "name": "L5",
            "category": "Action",
            "description": "Random action node",
            "class": "RandomActionNode",
            "module": "btcm.examples.random.random_bt"
        }
    },
    "state": {
        "variables": {
            "T1": "T1 is a variable in the random state.",
            "T2": "T2 is a variable in the random state.",
            "T3": "T3 is a variable in the random state.",
            "T4": "T4 is a variable in the random state.",
            "T5": "T5 is a variable in the random state.",
            "T6": "T6 is a variable in the random state.",
            "I1": "I1 is a variable in the random state.",
            "I2": "I2 is a variable in the random state.",
            "I3": "I3 is a variable in the random state.",
            "B1": "B1 is a variable in the random state.",
            "B2": "B2 is a variable in the random state.",
            "B3": "B3 is a variable in the random state."
        },
        "class": "RandomState",
        "module": "btcm.examples.random.random_state"
    },
    "0": {
        "0": {
            "state": {
                "T1": true,
                "T2": true,
                "T3": false,
                "T4": true,
                "T5": true,
                "T6": false,
                "I1": true,
                "I2": false,
                "I3": true,
                "B1": false,
                "B2": false,
                "B3": true
            }
        },
        "1": {
            "update": {
                "36c07167-b215-42fa-a22a-45da71b31e9d": {
                    "name": "L0",
                    "status": "Status.FAILURE",
                    "action": "NullAction"
                }
            },
            "state": {
                "T1": true,
                "T2": true,
                "T3": false,
                "T4": true,
                "T5": true,
                "T6": false,
                "I1": true,
                "I2": false,
                "I3": true,
                "B1": false,
                "B2": false,
                "B3": true
            }
        },
        "2": {
            "update": {
                "84946059-dbd2-49e8-988d-6d2af224957e": {
                    "name": "L1",
                    "status": "Status.FAILURE",
                    "action": "NullAction"
                }
            },
            "state": {
                "T1": true,
                "T2": true,
                "T3": false,
                "T4": true,
                "T5": true,
                "T6": false,
                "I1": true,
                "I2": false,
                "I3": true,
                "B1": false,
                "B2": false,
                "B3": true
            }
        },
        "3": {
            "update": {
                "8bd5c731-3a25-48ad-98a6-e3f51efa7135": {
                    "name": "L2",
                    "status": "Status.SUCCESS",
                    "action": "NullAction"
                }
            },
            "state": {
                "T1": true,
                "T2": true,
                "T3": false,
                "T4": true,
                "T5": true,
                "T6": false,
                "I1": true,
                "I2": false,
                "I3": true,
                "B1": false,
                "B2": false,
                "B3": true
            }
        },
        "4": {
            "update": {
                "a8894abf-7ace-4a54-b4a5-44444ad64835": {
                    "name": "C1",
                    "status": "Status.SUCCESS"
                }
            },
            "state": {
                "T1": true,
                "T2": true,
                "T3": false,
                "T4": true,
                "T5": true,
                "T6": false,
                "I1": true,
                "I2": false,
                "I3": true,
                "B1": false,
                "B2": false,
                "B3": true
            }
        },
        "5": {
            "update": {
                "79cf8073-b5f2-4359-a5b0-3bb3c68bce38": {
                    "name": "C0",
                    "status": "Status.SUCCESS"
                }
            },
            "state": {
                "T1": true,
                "T2": true,
                "T3": false,
                "T4": true,
                "T5": true,
                "T6": false,
                "I1": true,
                "I2": false,
                "I3": true,
                "B1": false,
                "B2": false,
                "B3": true
            }
        }
    }
}