{
    "tree": {
        "fbe082c6-d52d-48d3-8a5c-5a4ba5ac4b3f": {
            "name": "C0",
            "category": "Fallback",
            "memory": false,
            "children": [
                "e8001a9f-40a3-4c05-8700-0c870114ae95",
                "f4abcb33-f59a-4b1d-9843-f620bf434f50"
            ]
        },
        "e8001a9f-40a3-4c05-8700-0c870114ae95": {
            "name": "L0",
            "category": "Condition",
            "description": "Random condition node",
            "class": "RandomConditionNode",
            "module": "btcm.examples.random.random_bt"
        },
        "f4abcb33-f59a-4b1d-9843-f620bf434f50": {
            "name": "C1",
            "category": "Fallback",
            "memory": false,
            "children": [
                "1bd1a27b-a5c3-40a3-8423-0893439ade0e",
                "a7190c6f-b593-4285-9062-c7683daa79f6",
                "73b56a3f-9850-4c7b-b29b-5b4445a393a6"
            ]
        },
        "1bd1a27b-a5c3-40a3-8423-0893439ade0e": {
            "name": "L1",
            "category": "Action",
            "description": "Random action node",
            "class": "RandomActionNode",
            "module": "btcm.examples.random.random_bt"
        },
        "a7190c6f-b593-4285-9062-c7683daa79f6": {
            "name": "L2",
            "category": "Action",
            "description": "Random action node",
            "class": "RandomActionNode",
            "module": "btcm.examples.random.random_bt"
        },
        "73b56a3f-9850-4c7b-b29b-5b4445a393a6": {
            "name": "L3",
            "category": "Condition",
            "description": "Random condition node",
            "class": "RandomConditionNode",
            "module": "btcm.examples.random.random_bt"
        }
    },
    "state": {
        "variables": {
            "T1": "T1 is a variable in the random state.",
            "T2": "T2 is a variable in the random state.",
            "T3": "T3 is a variable in the random state.",
            "T4": "T4 is a variable in the random state.",
            "T5": "T5 is a variable in the random state.",
            "T6": "T6 is a variable in the random state.",
            "I1": "I1 is a variable in the random state.",
            "I2": "I2 is a variable in the random state.",
            "I3": "I3 is a variable in the random state.",
            "B1": "B1 is a variable in the random state.",
            "B2": "B2 is a variable in the random state.",
            "B3": "B3 is a variable in the random state."
        },
        "class": "RandomState",
        "module": "btcm.examples.random.random_state"
    },
    "0": {
        "0": {
            "state": {
                "T1": false,
                "T2": true,
                "T3": false,
                "T4": true,
                "T5": true,
                "T6": true,
                "I1": false,
                "I2": true,
                "I3": false,
                "B1": true,
                "B2": true,
                "B3": true
            }
        },
        "1": {
            "update": {
                "e8001a9f-40a3-4c05-8700-0c870114ae95": {
                    "name": "L0",
                    "status": "Status.FAILURE",
                    "action": "NullAction"
                }
            },
            "state": {
                "T1": false,
                "T2": true,
                "T3": false,
                "T4": true,
                "T5": true,
                "T6": true,
                "I1": false,
                "I2": true,
                "I3": false,
                "B1": true,
                "B2": true,
                "B3": true
            }
        },
        "2": {
            "update": {
                "1bd1a27b-a5c3-40a3-8423-0893439ade0e": {
                    "name": "L1",
                    "status": "Status.FAILURE",
                    "action": "RandomAction2"
                }
            },
            "state": {
                "T1": false,
                "T2": true,
                "T3": false,
                "T4": true,
                "T5": true,
                "T6": true,
                "I1": false,
                "I2": true,
                "I3": false,
                "B1": true,
                "B2": true,
                "B3": true
            }
        },
        "3": {
            "update": {
                "a7190c6f-b593-4285-9062-c7683daa79f6": {
                    "name": "L2",
                    "status": "Status.SUCCESS",
                    "action": "RandomAction3"
                }
            },
            "state": {
                "T1": false,
                "T2": true,
                "T3": false,
                "T4": true,
                "T5": true,
                "T6": true,
                "I1": false,
                "I2": true,
                "I3": false,
                "B1": true,
                "B2": true,
                "B3": true
            }
        },
        "4": {
            "update": {
                "f4abcb33-f59a-4b1d-9843-f620bf434f50": {
                    "name": "C1",
                    "status": "Status.SUCCESS"
                }
            },
            "state": {
                "T1": false,
                "T2": true,
                "T3": false,
                "T4": true,
                "T5": true,
                "T6": true,
                "I1": false,
                "I2": true,
                "I3": false,
                "B1": true,
                "B2": true,
                "B3": true
            }
        },
        "5": {
            "update": {
                "fbe082c6-d52d-48d3-8a5c-5a4ba5ac4b3f": {
                    "name": "C0",
                    "status": "Status.SUCCESS"
                }
            },
            "state": {
                "T1": false,
                "T2": true,
                "T3": false,
                "T4": true,
                "T5": true,
                "T6": true,
                "I1": false,
                "I2": true,
                "I3": false,
                "B1": true,
                "B2": true,
                "B3": true
            }
        }
    }
}