{
    "tree": {
        "88f3d4b3-4366-4c9c-b789-09d1bea0832c": {
            "name": "C0",
            "category": "Fallback",
            "memory": false,
            "children": [
                "cd8d6de1-6af7-42c7-96be-34f52e406100",
                "1906f473-a57f-40ea-8470-59ef9845327e",
                "474eff5b-1328-4381-871c-510dc6504949",
                "70b614d0-88c8-4589-a6b7-552ed44a7be3"
            ]
        },
        "cd8d6de1-6af7-42c7-96be-34f52e406100": {
            "name": "C1",
            "category": "Sequence",
            "memory": false,
            "children": [
                "40825ee8-fd95-4882-80df-1dd04f561c79",
                "85509b5b-68f3-489b-8d2b-5c91b13530c4"
            ]
        },
        "40825ee8-fd95-4882-80df-1dd04f561c79": {
            "name": "L2",
            "category": "Action",
            "description": "Random action node",
            "class": "RandomActionNode",
            "module": "btcm.examples.random.random_bt"
        },
        "85509b5b-68f3-489b-8d2b-5c91b13530c4": {
            "name": "L3",
            "category": "Condition",
            "description": "Random condition node",
            "class": "RandomConditionNode",
            "module": "btcm.examples.random.random_bt"
        },
        "1906f473-a57f-40ea-8470-59ef9845327e": {
            "name": "C2",
            "category": "Sequence",
            "memory": false,
            "children": [
                "576577c1-c498-4dda-bdae-c5ff03bbb81f",
                "93d46349-5f61-4733-b453-d6b06fbab459"
            ]
        },
        "576577c1-c498-4dda-bdae-c5ff03bbb81f": {
            "name": "C3",
            "category": "Fallback",
            "memory": false,
            "children": [
                "de731600-f43d-4ef3-918c-325efb14d211",
                "0c822b18-b9da-4f38-a7ff-11399ac85b5b"
            ]
        },
        "de731600-f43d-4ef3-918c-325efb14d211": {
            "name": "C4",
            "category": "Fallback",
            "memory": false,
            "children": [
                "d04a7fd9-c496-488a-93d4-a347abb67816",
                "65b00c91-9433-4dbc-a4a4-0e5e313618ee"
            ]
        },
        "d04a7fd9-c496-488a-93d4-a347abb67816": {
            "name": "L5",
            "category": "Condition",
            "description": "Random condition node",
            "class": "RandomConditionNode",
            "module": "btcm.examples.random.random_bt"
        },
        "65b00c91-9433-4dbc-a4a4-0e5e313618ee": {
            "name": "L6",
            "category": "Condition",
            "description": "Random condition node",
            "class": "RandomConditionNode",
            "module": "btcm.examples.random.random_bt"
        },
        "0c822b18-b9da-4f38-a7ff-11399ac85b5b": {
            "name": "L4",
            "category": "Condition",
            "description": "Random condition node",
            "class": "RandomConditionNode",
            "module": "btcm.examples.random.random_bt"
        },
        "93d46349-5f61-4733-b453-d6b06fbab459": {
            "name": "L0",
            "category": "Action",
            "description": "Random action node",
            "class": "RandomActionNode",
            "module": "btcm.examples.random.random_bt"
        },
        "474eff5b-1328-4381-871c-510dc6504949": {
            "name": "L1",
            "category": "Condition",
            "description": "Random condition node",
            "class": "RandomConditionNode",
            "module": "btcm.examples.random.random_bt"
        },
        "70b614d0-88c8-4589-a6b7-552ed44a7be3": {
            "name": "L7",
            "category": "Action",
            "description": "Random action node",
            "class": "RandomActionNode",
            "module": "btcm.examples.random.random_bt"
        }
    },
    "state": {
        "variables": {
            "T1": "T1 is a variable in the random state.",
            "T2": "T2 is a variable in the random state.",
            "T3": "T3 is a variable in the random state.",
            "T4": "T4 is a variable in the random state.",
            "I1": "I1 is a variable in the random state.",
            "I2": "I2 is a variable in the random state.",
            "B1": "B1 is a variable in the random state.",
            "B2": "B2 is a variable in the random state."
        },
        "class": "RandomState",
        "module": "btcm.examples.random.random_state"
    },
    "0": {
        "0": {
            "state": {
                "T1": true,
                "T2": true,
                "T3": false,
                "T4": true,
                "I1": true,
                "I2": false,
                "B1": true,
                "B2": true
            }
        },
        "1": {
            "update": {
                "40825ee8-fd95-4882-80df-1dd04f561c79": {
                    "name": "L2",
                    "status": "Status.SUCCESS",
                    "action": "RandomAction0"
                }
            },
            "state": {
                "T1": true,
                "T2": true,
                "T3": false,
                "T4": true,
                "I1": true,
                "I2": false,
                "B1": true,
                "B2": true
            }
        },
        "2": {
            "update": {
                "85509b5b-68f3-489b-8d2b-5c91b13530c4": {
                    "name": "L3",
                    "status": "Status.SUCCESS",
                    "action": "NullAction"
                }
            },
            "state": {
                "T1": true,
                "T2": true,
                "T3": false,
                "T4": true,
                "I1": true,
                "I2": false,
                "B1": true,
                "B2": true
            }
        },
        "3": {
            "update": {
                "cd8d6de1-6af7-42c7-96be-34f52e406100": {
                    "name": "C1",
                    "status": "Status.SUCCESS"
                }
            },
            "state": {
                "T1": true,
                "T2": true,
                "T3": false,
                "T4": true,
                "I1": true,
                "I2": false,
                "B1": true,
                "B2": true
            }
        },
        "4": {
            "update": {
                "88f3d4b3-4366-4c9c-b789-09d1bea0832c": {
                    "name": "C0",
                    "status": "Status.SUCCESS"
                }
            },
            "state": {
                "T1": true,
                "T2": true,
                "T3": false,
                "T4": true,
                "I1": true,
                "I2": false,
                "B1": true,
                "B2": true
            }
        }
    }
}