{
    "tree": {
        "b5d50cba-d832-4342-bb1a-4f56d9e08b8c": {
            "name": "C0",
            "category": "Fallback",
            "memory": false,
            "children": [
                "830d6847-3ef6-4730-8e02-6f042617e150",
                "5a9a86b8-c3bb-4f19-867a-bd31eeaf8fb9",
                "1c544fee-b85c-465e-a3cf-fe06c4e0e1b4",
                "70a6487d-5f6f-4344-89bd-aa997d546d0e"
            ]
        },
        "830d6847-3ef6-4730-8e02-6f042617e150": {
            "name": "L0",
            "category": "Condition",
            "description": "Random condition node",
            "class": "RandomConditionNode",
            "module": "btcm.examples.random.random_bt"
        },
        "5a9a86b8-c3bb-4f19-867a-bd31eeaf8fb9": {
            "name": "L1",
            "category": "Action",
            "description": "Random action node",
            "class": "RandomActionNode",
            "module": "btcm.examples.random.random_bt"
        },
        "1c544fee-b85c-465e-a3cf-fe06c4e0e1b4": {
            "name": "L2",
            "category": "Condition",
            "description": "Random condition node",
            "class": "RandomConditionNode",
            "module": "btcm.examples.random.random_bt"
        },
        "70a6487d-5f6f-4344-89bd-aa997d546d0e": {
            "name": "L3",
            "category": "Action",
            "description": "Random action node",
            "class": "RandomActionNode",
            "module": "btcm.examples.random.random_bt"
        }
    },
    "state": {
        "variables": {
            "T1": "T1 is a variable in the random state.",
            "T2": "T2 is a variable in the random state.",
            "T3": "T3 is a variable in the random state.",
            "T4": "T4 is a variable in the random state.",
            "I1": "I1 is a variable in the random state.",
            "I2": "I2 is a variable in the random state.",
            "B1": "B1 is a variable in the random state.",
            "B2": "B2 is a variable in the random state."
        },
        "class": "RandomState",
        "module": "btcm.examples.random.random_state"
    },
    "0": {
        "0": {
            "state": {
                "T1": true,
                "T2": false,
                "T3": true,
                "T4": true,
                "I1": false,
                "I2": true,
                "B1": true,
                "B2": true
            }
        },
        "1": {
            "update": {
                "830d6847-3ef6-4730-8e02-6f042617e150": {
                    "name": "L0",
                    "status": "Status.FAILURE",
                    "action": "NullAction"
                }
            },
            "state": {
                "T1": true,
                "T2": false,
                "T3": true,
                "T4": true,
                "I1": false,
                "I2": true,
                "B1": true,
                "B2": true
            }
        },
        "2": {
            "update": {
                "5a9a86b8-c3bb-4f19-867a-bd31eeaf8fb9": {
                    "name": "L1",
                    "status": "Status.FAILURE",
                    "action": "RandomAction3"
                }
            },
            "state": {
                "T1": true,
                "T2": false,
                "T3": true,
                "T4": true,
                "I1": false,
                "I2": true,
                "B1": true,
                "B2": true
            }
        },
        "3": {
            "update": {
                "1c544fee-b85c-465e-a3cf-fe06c4e0e1b4": {
                    "name": "L2",
                    "status": "Status.FAILURE",
                    "action": "NullAction"
                }
            },
            "state": {
                "T1": true,
                "T2": false,
                "T3": true,
                "T4": true,
                "I1": false,
                "I2": true,
                "B1": true,
                "B2": true
            }
        },
        "4": {
            "update": {
                "70a6487d-5f6f-4344-89bd-aa997d546d0e": {
                    "name": "L3",
                    "status": "Status.SUCCESS",
                    "action": "RandomAction3"
                }
            },
            "state": {
                "T1": true,
                "T2": false,
                "T3": true,
                "T4": true,
                "I1": false,
                "I2": true,
                "B1": true,
                "B2": true
            }
        },
        "5": {
            "update": {
                "b5d50cba-d832-4342-bb1a-4f56d9e08b8c": {
                    "name": "C0",
                    "status": "Status.SUCCESS"
                }
            },
            "state": {
                "T1": true,
                "T2": false,
                "T3": true,
                "T4": true,
                "I1": false,
                "I2": true,
                "B1": true,
                "B2": true
            }
        }
    }
}