{
    "tree": {
        "936ab6d4-0929-4f4b-9bd7-f0997c3ac13c": {
            "name": "C0",
            "category": "Sequence",
            "memory": false,
            "children": [
                "aef90ed7-3a96-4c7b-89ed-141dcc2e7445",
                "0ae0dc9e-9da7-443b-863b-5a701480f53a",
                "52758122-958b-428b-9666-ec3e1bb81cb2"
            ]
        },
        "aef90ed7-3a96-4c7b-89ed-141dcc2e7445": {
            "name": "L0",
            "category": "Condition",
            "description": "Random condition node",
            "class": "RandomConditionNode",
            "module": "btcm.examples.random.random_bt"
        },
        "0ae0dc9e-9da7-443b-863b-5a701480f53a": {
            "name": "C1",
            "category": "Sequence",
            "memory": false,
            "children": [
                "111ab7da-4ea8-4e41-8338-2ae066950ac4",
                "da514c9c-9621-43a3-9413-9e73f16f4955"
            ]
        },
        "111ab7da-4ea8-4e41-8338-2ae066950ac4": {
            "name": "L1",
            "category": "Condition",
            "description": "Random condition node",
            "class": "RandomConditionNode",
            "module": "btcm.examples.random.random_bt"
        },
        "da514c9c-9621-43a3-9413-9e73f16f4955": {
            "name": "L2",
            "category": "Action",
            "description": "Random action node",
            "class": "RandomActionNode",
            "module": "btcm.examples.random.random_bt"
        },
        "52758122-958b-428b-9666-ec3e1bb81cb2": {
            "name": "L3",
            "category": "Condition",
            "description": "Random condition node",
            "class": "RandomConditionNode",
            "module": "btcm.examples.random.random_bt"
        }
    },
    "state": {
        "variables": {
            "T1": "T1 is a variable in the random state.",
            "T2": "T2 is a variable in the random state.",
            "T3": "T3 is a variable in the random state.",
            "T4": "T4 is a variable in the random state.",
            "I1": "I1 is a variable in the random state.",
            "I2": "I2 is a variable in the random state.",
            "B1": "B1 is a variable in the random state.",
            "B2": "B2 is a variable in the random state."
        },
        "class": "RandomState",
        "module": "btcm.examples.random.random_state"
    },
    "0": {
        "0": {
            "state": {
                "T1": true,
                "T2": false,
                "T3": false,
                "T4": false,
                "I1": true,
                "I2": false,
                "B1": false,
                "B2": false
            }
        },
        "1": {
            "update": {
                "aef90ed7-3a96-4c7b-89ed-141dcc2e7445": {
                    "name": "L0",
                    "status": "Status.SUCCESS",
                    "action": "NullAction"
                }
            },
            "state": {
                "T1": true,
                "T2": false,
                "T3": false,
                "T4": false,
                "I1": true,
                "I2": false,
                "B1": false,
                "B2": false
            }
        },
        "2": {
            "update": {
                "111ab7da-4ea8-4e41-8338-2ae066950ac4": {
                    "name": "L1",
                    "status": "Status.SUCCESS",
                    "action": "NullAction"
                }
            },
            "state": {
                "T1": true,
                "T2": false,
                "T3": false,
                "T4": false,
                "I1": true,
                "I2": false,
                "B1": false,
                "B2": false
            }
        },
        "3": {
            "update": {
                "da514c9c-9621-43a3-9413-9e73f16f4955": {
                    "name": "L2",
                    "status": "Status.FAILURE",
                    "action": "RandomAction2"
                }
            },
            "state": {
                "T1": true,
                "T2": false,
                "T3": false,
                "T4": false,
                "I1": true,
                "I2": false,
                "B1": false,
                "B2": false
            }
        },
        "4": {
            "update": {
                "0ae0dc9e-9da7-443b-863b-5a701480f53a": {
                    "name": "C1",
                    "status": "Status.FAILURE"
                }
            },
            "state": {
                "T1": true,
                "T2": false,
                "T3": false,
                "T4": false,
                "I1": true,
                "I2": false,
                "B1": false,
                "B2": false
            }
        },
        "5": {
            "update": {
                "936ab6d4-0929-4f4b-9bd7-f0997c3ac13c": {
                    "name": "C0",
                    "status": "Status.FAILURE"
                }
            },
            "state": {
                "T1": true,
                "T2": false,
                "T3": false,
                "T4": false,
                "I1": true,
                "I2": false,
                "B1": false,
                "B2": false
            }
        }
    }
}