{
    "tree": {
        "d6c4a74f-4cb4-4910-9427-29b1c4e94e27": {
            "name": "C0",
            "category": "Sequence",
            "memory": false,
            "children": [
                "d7eae231-5ff1-432b-8f06-ffabe87b0ff6",
                "cc0cda26-d5bf-4e5e-bacb-3d6b5f501ce3",
                "1bc4ccde-1caa-4a5c-b74b-6c38968f315b",
                "aea2b9a5-8565-46b8-b586-ee202ca20f8e"
            ]
        },
        "d7eae231-5ff1-432b-8f06-ffabe87b0ff6": {
            "name": "L0",
            "category": "Condition",
            "description": "Random condition node",
            "class": "RandomConditionNode",
            "module": "btcm.examples.random.random_bt"
        },
        "cc0cda26-d5bf-4e5e-bacb-3d6b5f501ce3": {
            "name": "L1",
            "category": "Condition",
            "description": "Random condition node",
            "class": "RandomConditionNode",
            "module": "btcm.examples.random.random_bt"
        },
        "1bc4ccde-1caa-4a5c-b74b-6c38968f315b": {
            "name": "L2",
            "category": "Condition",
            "description": "Random condition node",
            "class": "RandomConditionNode",
            "module": "btcm.examples.random.random_bt"
        },
        "aea2b9a5-8565-46b8-b586-ee202ca20f8e": {
            "name": "L3",
            "category": "Action",
            "description": "Random action node",
            "class": "RandomActionNode",
            "module": "btcm.examples.random.random_bt"
        }
    },
    "state": {
        "variables": {
            "T1": "T1 is a variable in the random state.",
            "T2": "T2 is a variable in the random state.",
            "T3": "T3 is a variable in the random state.",
            "T4": "T4 is a variable in the random state.",
            "I1": "I1 is a variable in the random state.",
            "I2": "I2 is a variable in the random state.",
            "B1": "B1 is a variable in the random state.",
            "B2": "B2 is a variable in the random state."
        },
        "class": "RandomState",
        "module": "btcm.examples.random.random_state"
    },
    "0": {
        "0": {
            "state": {
                "T1": true,
                "T2": false,
                "T3": false,
                "T4": false,
                "I1": true,
                "I2": false,
                "B1": true,
                "B2": true
            }
        },
        "1": {
            "update": {
                "d7eae231-5ff1-432b-8f06-ffabe87b0ff6": {
                    "name": "L0",
                    "status": "Status.SUCCESS",
                    "action": "NullAction"
                }
            },
            "state": {
                "T1": true,
                "T2": false,
                "T3": false,
                "T4": false,
                "I1": true,
                "I2": false,
                "B1": true,
                "B2": true
            }
        },
        "2": {
            "update": {
                "cc0cda26-d5bf-4e5e-bacb-3d6b5f501ce3": {
                    "name": "L1",
                    "status": "Status.FAILURE",
                    "action": "NullAction"
                }
            },
            "state": {
                "T1": true,
                "T2": false,
                "T3": false,
                "T4": false,
                "I1": true,
                "I2": false,
                "B1": true,
                "B2": true
            }
        },
        "3": {
            "update": {
                "d6c4a74f-4cb4-4910-9427-29b1c4e94e27": {
                    "name": "C0",
                    "status": "Status.FAILURE"
                }
            },
            "state": {
                "T1": true,
                "T2": false,
                "T3": false,
                "T4": false,
                "I1": true,
                "I2": false,
                "B1": true,
                "B2": true
            }
        }
    }
}